LICENSE
rushmore_tools/__init__.py
rushmore_tools/_api/__init__.py
rushmore_tools/_api/api.py
rushmore_tools/rushmore_extractor.py
rushmore_tools-1.0.2.dist-info/LICENSE
rushmore_tools-1.0.2.dist-info/METADATA
rushmore_tools-1.0.2.dist-info/WHEEL
rushmore_tools-1.0.2.dist-info/RECORD
