Metadata-Version: 2.1
Name: rushmore-tools
Version: 1.0.2
Summary: 
Home-page: https://github.com/THREE60-Energy/rushmore-tools
License: Apache-2.0
Author: Marcus Risanger
Author-email: 69350948+MarcusRisanger@users.noreply.github.com
Requires-Python: >=3.10,<4.0
Classifier: License :: OSI Approved :: Apache Software License
Classifier: Programming Language :: Python :: 3
Classifier: Programming Language :: Python :: 3.10
Classifier: Programming Language :: Python :: 3.11
Requires-Dist: requests (>=2.27.1,<3.0.0)
Project-URL: Repository, https://github.com/THREE60-Energy/rushmore-tools
